discord_ext/__init__.py
discord_ext/about.py
discord_ext/api.py
discord_ext/cli.py
discord_ext/utils.py
discord_feed_bot-0.0.4.dist-info/LICENSE
discord_feed_bot-0.0.4.dist-info/METADATA
discord_feed_bot-0.0.4.dist-info/WHEEL
discord_feed_bot-0.0.4.dist-info/top_level.txt
discord_feed_bot-0.0.4.dist-info/RECORD
