Metadata-Version: 2.1
Name: discord-feed-bot
Version: 0.0.4
Summary: Discord bot for automating RSS feed updates.
Home-page: https://github.com/Py-Contributors/rssfeed
Author: PyContributors
Author-email: deepak008@live.com
Keywords: rssfeed,rssfeedcli,rssfeed-cli
Classifier: Development Status :: 3 - Alpha
Classifier: Programming Language :: Python :: 3
Classifier: Operating System :: OS Independent
Classifier: Intended Audience :: End Users/Desktop
Classifier: Intended Audience :: Developers
Requires-Python: >=3.1
License-File: LICENSE
Requires-Dist: requests (==2.28.1)
Requires-Dist: discord-webhook (==1.0.0)
Requires-Dist: colorama (==0.4.6)
